pystructs/__init__.py
pystructs/data_structures.py
pystructs/validators.py
pystructs_utils-0.1.1.dist-info/licenses/LICENSE
pystructs_utils-0.1.1.dist-info/METADATA
pystructs_utils-0.1.1.dist-info/WHEEL
pystructs_utils-0.1.1.dist-info/top_level.txt
pystructs_utils-0.1.1.dist-info/RECORD
