Metadata-Version: 2.4
Name: pystructs-utils
Version: 0.1.1
Summary: Functional utilities for nested data structures and validations
Author: albertoh88
License: MIT
Requires-Python: >=3.8
License-File: LICENSE
Dynamic: author
Dynamic: description
Dynamic: description-content-type
Dynamic: license
Dynamic: license-file
Dynamic: requires-python
Dynamic: summary
